jdj_tags/__init__.py
jdj_tags/extensions.py
jinja2_django_tags-0.5.dist-info/DESCRIPTION.rst
jinja2_django_tags-0.5.dist-info/METADATA
jinja2_django_tags-0.5.dist-info/RECORD
jinja2_django_tags-0.5.dist-info/WHEEL
jinja2_django_tags-0.5.dist-info/metadata.json
jinja2_django_tags-0.5.dist-info/top_level.txt
